[
  {"device_name":"交换机1","interface_slot":"1213","interface_name":"23","interface_description":"N交换机1"},
  {"device_name":"交换机2","interface_slot":"1212","interface_name":"22","interface_description":"N交换机2"},
  {"device_name":"交换机3","interface_slot":"1213","interface_name":"23","interface_description":"N交换机3"},
  {"device_name":"交换机4","interface_slot":"1214","interface_name":"24","interface_description":"N交换机4"},
  {"device_name":"交换机5","interface_slot":"1215","interface_name":"25","interface_description":"N交换机5"},
  {"device_name":"交换机6","interface_slot":"1216","interface_name":"26","interface_description":"N交换机6"},
  {"device_name":"交换机6","interface_slot":"1216","interface_name":"26","interface_description":"N交换机6"},
  {"device_name":"交换机6","interface_slot":"1216","interface_name":"26","interface_description":"N交换机6"},
  {"device_name":"交换机6","interface_slot":"1216","interface_name":"26","interface_description":"N交换机6"},
  {"device_name":"交换机6","interface_slot":"1216","interface_name":"26","interface_description":"N交换机6"},
  {"device_name":"交换机6","interface_slot":"1216","interface_name":"26","interface_description":"N交换机6"},
  {"device_name":"交换机6","interface_slot":"1216","interface_name":"26","interface_description":"N交换机6"},
  {"device_name":"交换机6","interface_slot":"1216","interface_name":"26","interface_description":"N交换机6"},
  {"device_name":"交换机6","interface_slot":"1216","interface_name":"26","interface_description":"N交换机6"},
  {"device_name":"交换机6","interface_slot":"1216","interface_name":"26","interface_description":"N交换机6"},
  {"device_name":"交换机6","interface_slot":"1216","interface_name":"26","interface_description":"N交换机6"},
  {"device_name":"交换机6","interface_slot":"1216","interface_name":"26","interface_description":"N交换机6"},
  {"device_name":"交换机6","interface_slot":"1216","interface_name":"26","interface_description":"N交换机6"},
  {"device_name":"交换机6","interface_slot":"1216","interface_name":"26","interface_description":"N交换机6"},
  {"device_name":"交换机6","interface_slot":"1216","interface_name":"26","interface_description":"N交换机6"},
  {"device_name":"交换机6","interface_slot":"1216","interface_name":"26","interface_description":"N交换机6"},
  {"device_name":"交换机6","interface_slot":"1216","interface_name":"26","interface_description":"N交换机6"},
  {"device_name":"交换机6","interface_slot":"1216","interface_name":"26","interface_description":"N交换机6"},
  {"device_name":"交换机6","interface_slot":"1216","interface_name":"26","interface_description":"N交换机6"},
  {"device_name":"交换机7","interface_slot":"1217","interface_name":"27","interface_description":"N交换机7"},
  {"device_name":"交换机8","interface_slot":"1218","interface_name":"28","interface_description":"N交换机8"}
]